contenttypes.basic-2.0-py3.11-nspkg.pth
contenttypes/basic/__init__.py
contenttypes/basic/configure.zcml
contenttypes/basic/contents.py
contenttypes/basic/interfaces.py
contenttypes/basic/permissions.py
contenttypes/basic/permissions.zcml
contenttypes/basic/setuphandlers.py
contenttypes/basic/testing.py
contenttypes/basic/upgrades.py
contenttypes/basic/upgrades.zcml
contenttypes/basic/behaviors/__init__.py
contenttypes/basic/behaviors/button_text.py
contenttypes/basic/behaviors/colour.py
contenttypes/basic/behaviors/configure.zcml
contenttypes/basic/behaviors/hide_text.py
contenttypes/basic/behaviors/icon.py
contenttypes/basic/behaviors/link.py
contenttypes/basic/behaviors/osmap.py
contenttypes/basic/behaviors/osmap_advanced.py
contenttypes/basic/behaviors/text_position.py
contenttypes/basic/browser/__init__.py
contenttypes/basic/browser/configure.zcml
contenttypes/basic/browser/default_view.pt
contenttypes/basic/browser/default_view.py
contenttypes/basic/browser/link.pt
contenttypes/basic/browser/link_redirect.pt
contenttypes/basic/browser/link_redirect.py
contenttypes/basic/browser/link_redirect_view.py
contenttypes/basic/browser/sprite.pt
contenttypes/basic/browser/sprite.py
contenttypes/basic/browser/overrides/.gitkeep
contenttypes/basic/browser/static/.gitkeep
contenttypes/basic/browser/static/osmap/leaflet-src.esm.js
contenttypes/basic/browser/static/osmap/leaflet-src.esm.js.map
contenttypes/basic/browser/static/osmap/leaflet-src.js
contenttypes/basic/browser/static/osmap/leaflet-src.js.map
contenttypes/basic/browser/static/osmap/leaflet.css
contenttypes/basic/browser/static/osmap/leaflet.js
contenttypes/basic/browser/static/osmap/leaflet.js.map
contenttypes/basic/browser/static/osmap/images/layers-2x.png
contenttypes/basic/browser/static/osmap/images/layers.png
contenttypes/basic/browser/static/osmap/images/marker-icon-2x.png
contenttypes/basic/browser/static/osmap/images/marker-icon.png
contenttypes/basic/browser/static/osmap/images/marker-shadow.png
contenttypes.basic-2.0.dist-info/LICENSE.GPL
contenttypes.basic-2.0.dist-info/LICENSE.rst
contenttypes.basic-2.0.dist-info/METADATA
contenttypes.basic-2.0.dist-info/WHEEL
contenttypes.basic-2.0.dist-info/entry_points.txt
contenttypes.basic-2.0.dist-info/namespace_packages.txt
contenttypes.basic-2.0.dist-info/top_level.txt
contenttypes.basic-2.0.dist-info/RECORD
